{
    "version": 5,
    "staticLocations": [
        {
            "key": "leftFootGrip",
            "overlayTransform": {
                "pos": {
                    "x": -0.23560604453086854,
                    "y": 0.6071305871009827,
                    "z": 0.44360655546188357
                },
                "rot": {
                    "x": 0.0,
                    "y": 0.0,
                    "z": 0.0
                }
            }
        },
        {
            "key": "metaPanel",
            "overlayTransform": {
                "pos": {
                    "x": 0.63897705078125,
                    "y": 0.47762352228164675,
                    "z": 0.1921326071023941
                },
                "rot": {
                    "x": 42.911827087402347,
                    "y": 65.78206634521485,
                    "z": 7.146819114685059
                }
            }
        },
        {
            "key": "srvJoystick",
            "overlayTransform": {
                "pos": {
                    "x": 0.26581311225891116,
                    "y": 0.7062139511108398,
                    "z": 0.43387454748153689
                },
                "rot": {
                    "x": 0.0,
                    "y": 0.0,
                    "z": 0.0
                }
            }
        },
        {
            "key": "fighterJoystick",
            "overlayTransform": {
                "pos": {
                    "x": 0.27000001072883608,
                    "y": 0.6000000238418579,
                    "z": 0.38999998569488528
                },
                "rot": {
                    "x": 0.0,
                    "y": 0.0,
                    "z": 0.0
                }
            }
        },
        {
            "key": "shipJoystick",
            "overlayTransform": {
                "pos": {
                    "x": 0.2867908477783203,
                    "y": 0.6661794185638428,
                    "z": 0.4457104504108429
                },
                "rot": {
                    "x": 0.0,
                    "y": 0.0,
                    "z": 0.0
                }
            }
        },
        {
            "key": "centerButtonPanel",
            "overlayTransform": {
                "pos": {
                    "x": 0.0027207210659980776,
                    "y": 0.6920153498649597,
                    "z": 0.5160055160522461
                },
                "rot": {
                    "x": 49.52472686767578,
                    "y": 0.5414090752601624,
                    "z": 358.9066162109375
                }
            }
        },
        {
            "key": "rightButtonPanel",
            "overlayTransform": {
                "pos": {
                    "x": 0.4675077497959137,
                    "y": 0.7682406902313232,
                    "z": 0.4763771593570709
                },
                "rot": {
                    "x": 26.14735221862793,
                    "y": 38.49590301513672,
                    "z": 2.6136627197265627
                }
            }
        },
        {
            "key": "leftButtonPanel",
            "overlayTransform": {
                "pos": {
                    "x": -0.3909476101398468,
                    "y": 0.762420654296875,
                    "z": 0.4999099671840668
                },
                "rot": {
                    "x": 28.721885681152345,
                    "y": 331.5639953613281,
                    "z": 0.5332037806510925
                }
            }
        },
        {
            "key": "shipPowerDistributionPanel",
            "overlayTransform": {
                "pos": {
                    "x": 0.49947473406791689,
                    "y": 0.762002170085907,
                    "z": 0.49824732542037966
                },
                "rot": {
                    "x": 27.10624122619629,
                    "y": 38.1968879699707,
                    "z": 358.3895568847656
                }
            }
        },
        {
            "key": "srvThrottle",
            "overlayTransform": {
                "pos": {
                    "x": -0.1575070321559906,
                    "y": 0.7746366262435913,
                    "z": 0.35048484802246096
                },
                "rot": {
                    "x": 349.89892578125,
                    "y": 1.563966989517212,
                    "z": 315.5614013671875
                }
            }
        },
        {
            "key": "shipThrottle",
            "overlayTransform": {
                "pos": {
                    "x": -0.17003656923770905,
                    "y": 0.7499767541885376,
                    "z": 0.35804516077041628
                },
                "rot": {
                    "x": 356.19403076171877,
                    "y": 0.23868925869464875,
                    "z": 1.3746482133865357
                }
            }
        },
        {
            "key": "fighterThrottle",
            "overlayTransform": {
                "pos": {
                    "x": -0.14658410847187043,
                    "y": 0.7448037266731262,
                    "z": 0.37246567010879519
                },
                "rot": {
                    "x": 359.8091125488281,
                    "y": 0.8057231903076172,
                    "z": 358.4627990722656
                }
            }
        },
        {
            "key": "fighterPowerDistributionPanel",
            "overlayTransform": {
                "pos": {
                    "x": 0.3099850118160248,
                    "y": 0.8310741782188416,
                    "z": 0.5320585370063782
                },
                "rot": {
                    "x": 17.104217529296876,
                    "y": 27.670324325561525,
                    "z": 356.9954833984375
                }
            }
        },
        {
            "key": "srvPowerDistributionPanel",
            "overlayTransform": {
                "pos": {
                    "x": 0.3499999940395355,
                    "y": 0.8999999761581421,
                    "z": 0.5
                },
                "rot": {
                    "x": 10.00000286102295,
                    "y": 34.99998474121094,
                    "z": -4.334721950272069e-7
                }
            }
        },
        {
            "key": "rightFootGrip",
            "overlayTransform": {
                "pos": {
                    "x": 0.272102952003479,
                    "y": 0.6236668825149536,
                    "z": 0.4453944265842438
                },
                "rot": {
                    "x": 0.0,
                    "y": 0.0,
                    "z": 0.0
                }
            }
        }
    ],
    "controlButtons": [],
    "booleanSettings": []
}